{"_id":"lodash._basevalues","_rev":"704281","name":"lodash._basevalues","description":"The modern build of lodash’s internal `baseValues` as a module.","dist-tags":{"latest":"3.0.0"},"maintainers":[{"name":"jdalton","email":"john.david.dalton@gmail.com"},{"name":"mathias","email":"mathias@qiwi.be"},{"name":"phated","email":"blaine.bublitz@gmail.com"}],"time":{"modified":"2015-01-26T15:50:49.000Z","created":"2015-01-26T15:28:08.615Z","3.0.0":"2015-01-26T15:28:08.615Z"},"users":{},"author":{"name":"John-David Dalton","email":"john.david.dalton@gmail.com","url":"http://allyoucanleet.com/"},"repository":{"type":"git","url":"https://github.com/lodash/lodash"},"versions":{"3.0.0":{"name":"lodash._basevalues","version":"3.0.0","description":"The modern build of lodash’s internal `baseValues` as a module.","homepage":"https://lodash.com/","icon":"https://lodash.com/icon.svg","license":"MIT","author":{"name":"John-David Dalton","email":"john.david.dalton@gmail.com","url":"http://allyoucanleet.com/"},"contributors":[{"name":"John-David Dalton","email":"john.david.dalton@gmail.com","url":"http://allyoucanleet.com/"},{"name":"Benjamin Tan","email":"demoneaux@gmail.com","url":"https://d10.github.io/"},{"name":"Blaine Bublitz","email":"blaine@iceddev.com","url":"http://www.iceddev.com/"},{"name":"Kit Cambridge","email":"github@kitcambridge.be","url":"http://kitcambridge.be/"},{"name":"Mathias Bynens","email":"mathias@qiwi.be","url":"https://mathiasbynens.be/"}],"repository":{"type":"git","url":"https://github.com/lodash/lodash"},"scripts":{"test":"echo \"See https://travis-ci.org/lodash/lodash-cli for testing details.\""},"bugs":{"url":"https://github.com/lodash/lodash/issues"},"_id":"lodash._basevalues@3.0.0","_shasum":"5b775762802bde3d3297503e26300820fdf661b7","_from":".","_npmVersion":"2.3.0","_nodeVersion":"0.10.35","_npmUser":{"name":"jdalton","email":"john.david.dalton@gmail.com"},"maintainers":[{"name":"jdalton","email":"john.david.dalton@gmail.com"},{"name":"mathias","email":"mathias@qiwi.be"},{"name":"phated","email":"blaine.bublitz@gmail.com"}],"dist":{"shasum":"5b775762802bde3d3297503e26300820fdf661b7","size":1959,"noattachment":false,"tarball":"http://registry.npm.taobao.org/lodash._basevalues/download/lodash._basevalues-3.0.0.tgz"},"directories":{},"publish_time":1422286088615,"_cnpm_publish_time":1422286088615}},"readme":"# lodash._basevalues v3.0.0\n\nThe [modern build](https://github.com/lodash/lodash/wiki/Build-Differences) of [lodash’s](https://lodash.com/) internal `baseValues` exported as a [Node.js](http://nodejs.org/)/[io.js](https://iojs.org/) module.\n\n## Installation\n\nUsing npm:\n\n```bash\n$ {sudo -H} npm i -g npm\n$ npm i --save lodash._basevalues\n```\n\nIn Node.js/io.js:\n\n```js\nvar baseValues = require('lodash._basevalues');\n```\n\nSee the [package source](https://github.com/lodash/lodash/blob/3.0.0-npm-packages/lodash._basevalues) for more details.\n","_attachments":{},"homepage":"https://lodash.com/","bugs":{"url":"https://github.com/lodash/lodash/issues"},"license":"MIT","_etag":"\"bf1-lmgJb7NyUFQ1ZaLaO52iqA\"","_cached":true}